ngrampro.py
ngrampro-0.0.7.dist-info/LICENSE
ngrampro-0.0.7.dist-info/METADATA
ngrampro-0.0.7.dist-info/WHEEL
ngrampro-0.0.7.dist-info/top_level.txt
ngrampro-0.0.7.dist-info/RECORD
