Metadata-Version: 2.1
Name: ngrampro
Version: 0.0.7
Summary: A python tool for k-mer generation from protein sequences
Home-page: https://github.com/deeprob/ngrampro.git
Author: Deepro Banerjee
Author-email: deepro.2.4@gmail.com
License: UNKNOWN
Platform: UNKNOWN
Classifier: Programming Language :: Python :: 3
Classifier: License :: OSI Approved :: MIT License
Classifier: Operating System :: OS Independent
Requires-Python: >=3.6
Requires-Dist: numpy
